MANIFEST.in
README.md
setup.cfg
setup.py
okcli/__init__.py
okcli/clibuffer.py
okcli/clistyle.py
okcli/clitoolbar.py
okcli/completion_refresher.py
okcli/config.py
okcli/encodingutils.py
okcli/filters.py
okcli/key_bindings.py
okcli/lexer.py
okcli/magic.py
okcli/main.py
okcli/okclirc
okcli/sqlcompleter.py
okcli/sqlexecute.py
okcli.egg-info/PKG-INFO
okcli.egg-info/SOURCES.txt
okcli.egg-info/dependency_links.txt
okcli.egg-info/entry_points.txt
okcli.egg-info/requires.txt
okcli.egg-info/top_level.txt
okcli/packages/__init__.py
okcli/packages/completion_engine.py
okcli/packages/parseutils.py
okcli/packages/special/__init__.py
okcli/packages/special/dbcommands.py
okcli/packages/special/favoritequeries.py
okcli/packages/special/iocommands.py
okcli/packages/special/main.py
okcli/packages/special/utils.py
test/test_completion_engine.py
test/test_completion_refresher.py
test/test_naive_completion.py
test/test_parseutils.py
test/test_smart_completion_public_schema_only.py
test/test_special_iocommands.py
test/test_special_main_commands.py